navy_ai/__init__.py
navy_ai/cli.py
navy_ai/config.py
navy_ai/renderer.py
navy_ai/providers/__init__.py
navy_ai/providers/base.py
navy_ai/providers/gemini.py
navy_ai/providers/ollama.py
navy_ai/providers/openai.py
navy_ai-0.1.8.dist-info/licenses/LICENSE
navy_ai-0.1.8.dist-info/METADATA
navy_ai-0.1.8.dist-info/WHEEL
navy_ai-0.1.8.dist-info/entry_points.txt
navy_ai-0.1.8.dist-info/top_level.txt
navy_ai-0.1.8.dist-info/RECORD
