Metadata-Version: 2.4
Name: navy-ai
Version: 0.1.8
Summary: Terminal-first AI assistant supporting local and cloud LLMs
Author-email: Zrnge <job@try-hack.com>
License: MIT
Project-URL: Homepage, https://github.com/Zrnge/navy-ai
Project-URL: Repository, https://github.com/Zrnge/navy-ai
Project-URL: Issues, https://github.com/Zrnge/navy-ai/issues
Requires-Python: >=3.9
License-File: LICENSE
Requires-Dist: typer>=0.9.0
Requires-Dist: rich>=13.0.0
Requires-Dist: httpx>=0.24.0
Dynamic: license-file
